chanoma/chanoma.cpython-38-x86_64-linux-gnu.so
chanoma/__init__.py
chanoma-0.1.2.dist-info/METADATA
chanoma-0.1.2.dist-info/WHEEL
chanoma-0.1.2.dist-info/top_level.txt
chanoma-0.1.2.dist-info/RECORD
