Metadata-Version: 2.1
Name: chanoma
Version: 0.1.2
Summary: chanoma is Characters Normalization library.文字列正規化処理用のライブラリです。
Home-page: https://github.com/booink/chanoma/tree/main/bindings/python3
Author: Booink
Author-email: booink.work@gmail.com
Keywords: japanese,normalize
Classifier: License :: OSI Approved :: MIT License
Classifier: Development Status :: 3 - Alpha
Classifier: Intended Audience :: Developers
Classifier: Programming Language :: Python
Classifier: Programming Language :: Rust
Classifier: Operating System :: POSIX
Classifier: Operating System :: MacOS :: MacOS X
